dropconnect/__init__.py
dropconnect/functional.py
dropconnect/nn.py
dropconnect-0.1.2.dist-info/LICENSE
dropconnect-0.1.2.dist-info/METADATA
dropconnect-0.1.2.dist-info/WHEEL
dropconnect-0.1.2.dist-info/RECORD
