Metadata-Version: 2.3
Name: dropconnect
Version: 0.1.2
Summary: A PyTorch implementation of dropconnect layers
License: MIT
Author: mr-mapache
Author-email: eric.m.cardozo@mi.unc.edu.ar
Requires-Python: >=3.12
Classifier: License :: OSI Approved :: MIT License
Classifier: Programming Language :: Python :: 3
Classifier: Programming Language :: Python :: 3.12
Classifier: Programming Language :: Python :: 3.13
